AUTHORS.rst
LICENSE
MANIFEST.in
setup.cfg
setup.py
django_kernel.egg-info/PKG-INFO
django_kernel.egg-info/SOURCES.txt
django_kernel.egg-info/dependency_links.txt
django_kernel.egg-info/not-zip-safe
django_kernel.egg-info/requires.txt
django_kernel.egg-info/top_level.txt
kernel/__init__.py
kernel/action.py
kernel/backends.py
kernel/constant.py
kernel/fields.py
kernel/filters.py
kernel/middleware.py
kernel/models.py
kernel/urls.py
kernel/utils.py
kernel/admin/__init__.py
kernel/admin/action.py
kernel/admin/mounting.py
kernel/admin/kernel/__init__.py
kernel/forms/__init__.py
kernel/forms/action.py
kernel/forms/auth.py
kernel/forms/user.py
kernel/managers/__init__.py
kernel/managers/page.py
kernel/managers/user.py
kernel/migrations/0001_initial.py
kernel/migrations/0002_auto_20160716_1315.py
kernel/migrations/0003_auto_20160719_1702.py
kernel/migrations/__init__.py
kernel/rest/__init__.py
kernel/rest/viewsets.py
kernel/templates/kernel/admin/action/move_to_group.html
kernel/views/__init__.py
kernel/views/login.py
kernel/views/mixin.py
kernel/views/user.py
kernel/widget/__init__.py