Metadata-Version: 1.1
Name: django-kernel
Version: 0.1
Summary: Kenrel Model for Django
Home-page: https://github.com/pycodi/django-kernel
Author: Nikita Kryuchkov
Author-email: info@pycode.net
License: MIT
Keywords: django-kernel
Platform: UNKNOWN
Classifier: Development Status :: 3 - Alpha
Classifier: Framework :: Django
Classifier: Framework :: Django :: 1.8
Classifier: Framework :: Django :: 1.9
Classifier: Intended Audience :: Developers
Classifier: Natural Language :: English
Classifier: Programming Language :: Python :: 3
Classifier: Programming Language :: Python :: 3.3
Classifier: Programming Language :: Python :: 3.4
Classifier: Programming Language :: Python :: 3.5
